omapi/__init__.py
omapi/_version.py
omapi/package_data.dat
omapi/data/__init__.py
omapi/data/mapping.py
omapi/lmb/__init__.py
omapi/lmb/log.py
vf_omapi_lib-0.0.3.dist-info/LICENSE.txt
vf_omapi_lib-0.0.3.dist-info/METADATA
vf_omapi_lib-0.0.3.dist-info/WHEEL
vf_omapi_lib-0.0.3.dist-info/top_level.txt
vf_omapi_lib-0.0.3.dist-info/RECORD
