Metadata-Version: 2.1
Name: vf-omapi-lib
Version: 0.0.3
Summary: Shared python code for VF-OMAPI components
Home-page: https://bitbucket.org/joerg_pauken/omapi_lib_python/
Author: Joerg Pauken
Author-email: joerg.pauken@vodafone.com
License: UNKNOWN
Keywords: OM,OMAPI,AWS,Lambda,APIG,MSK,Kafka
Platform: UNKNOWN
Classifier: Development Status :: 3 - Alpha
Classifier: Intended Audience :: Developers
Classifier: Topic :: Software Development :: Libraries
Classifier: License :: OSI Approved :: MIT License
Classifier: Programming Language :: Python :: 3.9
Requires-Python: >=3.9, <4
License-File: LICENSE.txt
Provides-Extra: dev
Requires-Dist: check-manifest ; extra == 'dev'
Provides-Extra: test
Requires-Dist: coverage ; extra == 'test'
